zy_gs/__init__.py
zy_gs/zy_gs/__init__.py
zy_gs/zy_gs/arguments/__init__.py
zy_gs/zy_gs/dtu_eval/eval.so
zy_gs/zy_gs/eval_tnt/compute_bbox_for_mesh.so
zy_gs/zy_gs/eval_tnt/config.so
zy_gs/zy_gs/eval_tnt/cull_mesh.so
zy_gs/zy_gs/eval_tnt/evaluate_single_scene.so
zy_gs/zy_gs/eval_tnt/evaluation.so
zy_gs/zy_gs/eval_tnt/help_func.so
zy_gs/zy_gs/eval_tnt/plot.so
zy_gs/zy_gs/eval_tnt/registration.so
zy_gs/zy_gs/eval_tnt/requirements.txt
zy_gs/zy_gs/eval_tnt/run.so
zy_gs/zy_gs/eval_tnt/trajectory_io.so
zy_gs/zy_gs/eval_tnt/util.so
zy_gs/zy_gs/gaussian_renderer/__init__.py
zy_gs/zy_gs/gaussian_renderer/network_gui.so
zy_gs/zy_gs/lpipsPyTorch/__init__.py
zy_gs/zy_gs/lpipsPyTorch/modules/lpips.so
zy_gs/zy_gs/lpipsPyTorch/modules/networks.so
zy_gs/zy_gs/lpipsPyTorch/modules/utils.so
zy_gs/zy_gs/mesh_extract/MeshExtract.so
zy_gs/zy_gs/mesh_extract/__init__.py
zy_gs/zy_gs/scene/__init__.py
zy_gs/zy_gs/scene/appearance_network.so
zy_gs/zy_gs/scene/cameras.so
zy_gs/zy_gs/scene/colmap_loader.so
zy_gs/zy_gs/scene/dataset_readers.so
zy_gs/zy_gs/scene/gaussian_model.so
zy_gs/zy_gs/submodules/diff-gaussian-rasterization/CMakeLists.txt
zy_gs/zy_gs/submodules/diff-gaussian-rasterization/third_party/glm/.appveyor.yml
zy_gs/zy_gs/submodules/diff-gaussian-rasterization/third_party/glm/.travis.yml
zy_gs/zy_gs/submodules/diff-gaussian-rasterization/third_party/glm/CMakeLists.txt
zy_gs/zy_gs/submodules/diff-gaussian-rasterization/third_party/glm/copying.txt
zy_gs/zy_gs/submodules/diff-gaussian-rasterization/third_party/glm/doc/manual/noise-perlin1.jpg
zy_gs/zy_gs/submodules/diff-gaussian-rasterization/third_party/glm/doc/manual/noise-perlin2.jpg
zy_gs/zy_gs/submodules/diff-gaussian-rasterization/third_party/glm/doc/manual/noise-perlin3.jpg
zy_gs/zy_gs/submodules/diff-gaussian-rasterization/third_party/glm/doc/manual/noise-simplex1.jpg
zy_gs/zy_gs/submodules/diff-gaussian-rasterization/third_party/glm/doc/manual/noise-simplex2.jpg
zy_gs-2.0.2.dist-info/METADATA
zy_gs-2.0.2.dist-info/WHEEL
zy_gs-2.0.2.dist-info/top_level.txt
zy_gs-2.0.2.dist-info/RECORD
