Metadata-Version: 2.4
Name: zy_gs
Version: 2.0.2
Summary: Gaussian Splatting based 3D reconstruction and training framework with RGB-D integration and mesh extraction utilities
License: Apache License 2.0
Requires-Dist: opencv-python==4.12.0.88
Requires-Dist: open3d==0.19.0
Requires-Dist: tqdm==4.67.1
Requires-Dist: trimesh==4.7.1
Dynamic: license
Dynamic: requires-dist
Dynamic: summary
